xrdtools/__init__.py
xrdtools/io.py
xrdtools/utils.py
xrdtools/data/schemas/XRDMeasurement10.xsd
xrdtools/data/schemas/XRDMeasurement11.xsd
xrdtools/data/schemas/XRDMeasurement12.xsd
xrdtools/data/schemas/XRDMeasurement13.xsd
xrdtools/data/schemas/XRDMeasurement14.xsd
xrdtools/data/schemas/XRDMeasurement15.xsd
xrdtools/tools/__init__.py
xrdtools/tools/clt.py
xrdtools-0.1.1.dist-info/METADATA
xrdtools-0.1.1.dist-info/RECORD
xrdtools-0.1.1.dist-info/WHEEL
xrdtools-0.1.1.dist-info/entry_points.txt
xrdtools-0.1.1.dist-info/top_level.txt
