Metadata-Version: 2.1
Name: xrdtools
Version: 0.1.1
Summary: A library to read .xrdml files
Home-page: https://github.com/paruch-group/xrdtools
Author: Benedikt Ziegler
Author-email: benediktziegler@gmail.com
License: MIT
Keywords: xrdml,read
Platform: UNKNOWN
Classifier: Development Status :: 3 - Alpha
Classifier: Environment :: Console
Classifier: Intended Audience :: Science/Research
Classifier: License :: OSI Approved :: MIT License
Classifier: Operating System :: MacOS :: MacOS X
Classifier: Operating System :: Microsoft :: Windows
Classifier: Operating System :: POSIX
Classifier: Programming Language :: Python
Classifier: Programming Language :: Python :: 2
Classifier: Programming Language :: Python :: 2.7
Classifier: Programming Language :: Python :: 3
Classifier: Programming Language :: Python :: 3.5
Classifier: Programming Language :: Python :: 3.6
Classifier: Topic :: Scientific/Engineering :: Physics
Requires-Dist: lxml (>=3.0)
Requires-Dist: numpy (>=1.7)
